calm/__init__.py
calm/atomdata.py
calm/cbarray.py
calm/chemistry.py
calm/constants.py
calm/convert.py
calm/material_parameters.py
calm/microstructure.py
calm/utils.py
calm/entities/Chemistry-0.1.json
calm/entities/ChemistryHist-0.1.json
calm/entities/ChemistryLognormal-0.1.json
calm/entities/ChemistrySizeDistribution-0.1.json
calm/entities/ChemistrySpatial-0.1.json
calm/entities/ChemistrySpatialSizeDistribution-0.1.json
calm/entities/ChemistryStoichiometricSizeDistribution-0.1.json
calm/entities/ChemistryVoxel-0.1.json
calm/entities/Constants-0.1.json
calm/entities/ExternalParameters-0.1.json
calm/entities/MaterialParameters-0.1.json
calm/entities/Microstructure-0.1.json
pypremod_calm-0.1.2.dist-info/METADATA
pypremod_calm-0.1.2.dist-info/WHEEL
pypremod_calm-0.1.2.dist-info/top_level.txt
pypremod_calm-0.1.2.dist-info/RECORD
