Metadata-Version: 2.1
Name: pypremod-calm
Version: 0.1.2
Summary: Python package for Computational ALuminium Metallurgy
Home-page: https://www.sintef.no
License: UNKNOWN
Platform: UNKNOWN
